<?xml version='1.0' encoding='UTF-8'?>
<Rows>
<Row><ProductName>Glow Assorted Loose Leaf Tea</ProductName> <Brand>VAHDAM</Brand> <Price>1995,00</Price> <DiscountPrice>1296,75</DiscountPrice> <Quantity>20 g</Quantity> <Category>Beverages</Category> <SubCategory>Leaf &amp; Dust Tea</SubCategory></Row>
<Row><ProductName>Atlantic Salmon Fish</ProductName> <Brand>Fresho</Brand> <Price>3879,00</Price> <DiscountPrice>2789,00</DiscountPrice> <Quantity>500 g</Quantity> <Category>Eggs, Meat &amp; Fish</Category> <SubCategory>Marine Water Fish</SubCategory></Row>
<Row><ProductName>Pomegranate - Peeled</ProductName> <Brand>Fresho</Brand> <Price>314,29</Price> <DiscountPrice>251,43</DiscountPrice> <Quantity>500 g</Quantity> <Category>Fruits &amp; Vegetables</Category> <SubCategory>Cut Fruit, Tender Coconut</SubCategory></Row>
<Row><ProductName>Pet Food - For Giant Junior Dogs, -</ProductName> <Brand>Royal Canin</Brand> <Price>10140,00</Price> <DiscountPrice>7605,00</DiscountPrice> <Quantity>15 kg</Quantity> <Category>Kitchen, Garden &amp; Pets</Category> <SubCategory>Pet Meals &amp; Treats</SubCategory></Row>
<Row><ProductName>Premium Care Diaper Pants - Large, 9-14 kg, Lotion with Aloe Vera</ProductName> <Brand>Pampers </Brand> <Price>3597,00</Price> <DiscountPrice>2311,00</DiscountPrice> <Quantity>132 pcs</Quantity> <Category>Baby Care</Category> <SubCategory>Diapers</SubCategory></Row>
<Row><ProductName>Eau De Toilette For Men</ProductName> <Brand>Mercedes-Benz</Brand> <Price>7150,00</Price> <DiscountPrice>5005,00</DiscountPrice> <Quantity>100 ml</Quantity> <Category>Beauty &amp; Hygiene</Category> <SubCategory>Eau De Toilette</SubCategory></Row>
<Row><ProductName>Organic - Extra Virgin Olive Oil</ProductName> <Brand>Phalada Pure &amp; Sure</Brand> <Price>4850,00</Price> <DiscountPrice>4607,50</DiscountPrice> <Quantity>5 L</Quantity> <Category>Foodgrains, Oil &amp; Masala</Category> <SubCategory>Organic Edible Oil, Ghee</SubCategory></Row>
<Row><ProductName>100% Pure Honey</ProductName> <Brand>BB Royal</Brand> <Price>900,00</Price> <DiscountPrice>558,00</DiscountPrice> <Quantity>2x1 kg</Quantity> <Category>Snacks &amp; Branded Foods</Category> <SubCategory>Honey</SubCategory></Row>
<Row><ProductName>Cheese Slices - Made From Cow Milk 663 g + Cheese Spread - Cream Cheese 100 g</ProductName> <Brand>Britannia</Brand> <Price>710,00</Price> <DiscountPrice>525,94</DiscountPrice> <Quantity>Combo</Quantity> <Category>Bakery, Cakes &amp; Dairy</Category> <SubCategory>Cheese</SubCategory></Row>
<Row><ProductName>Extra Light Olive Oil</ProductName> <Brand>Disano</Brand> <Price>7195,00</Price> <DiscountPrice>3165,80</DiscountPrice> <Quantity>5 L</Quantity> <Category>Gourmet &amp; World Food</Category> <SubCategory>Extra Virgin Olive Oil</SubCategory></Row>
<Row><ProductName>Laundry Detergent Liquid - Fresh Cotton, Lily &amp; Vanilla, Removes Tough Stains</ProductName> <Brand>Koparo Clean</Brand> <Price>3499,00</Price> <DiscountPrice>2274,35</DiscountPrice> <Quantity>5 L</Quantity> <Category>Cleaning &amp; Household</Category> <SubCategory>Detergent Powder, Liquid</SubCategory></Row>
</Rows>
